README.md
setup.cfg
setup.py
pygui_macro/__init__.py
pygui_macro/callbacks.py
pygui_macro/controller.py
pygui_macro/listener.py
pygui_macro/pygui_macro.py
pygui_macro/recoder.py
pygui_macro/runner.py
pygui_macro.egg-info/PKG-INFO
pygui_macro.egg-info/SOURCES.txt
pygui_macro.egg-info/dependency_links.txt
pygui_macro.egg-info/entry_points.txt
pygui_macro.egg-info/requires.txt
pygui_macro.egg-info/top_level.txt
pygui_macro.egg-info/zip-safe