Metadata-Version: 1.0
Name: pygui-macro
Version: 0.1.4
Summary: Cross-platform gui macro command tool with python, automate your keyboard and mouse.
Home-page: https://github.com/haoflynet/pygui-macro
Author: haoflynet
Author-email: haoflynet@gmail.com
License: MIT
Keywords: gui macro automate keyboard mouse
Platform: UNKNOWN
